sweepy/__init__.py
sweepy/cli copy.py
sweepy/cli.py
sweepy_cli-0.1.7.dist-info/METADATA
sweepy_cli-0.1.7.dist-info/WHEEL
sweepy_cli-0.1.7.dist-info/entry_points.txt
sweepy_cli-0.1.7.dist-info/licenses/LICENSE
sweepy_cli-0.1.7.dist-info/RECORD
