Metadata-Version: 2.4
Name: sweepy-cli
Version: 0.1.7
Summary: Sweep away unused imports from your codebase
License-Expression: MIT
License-File: LICENSE
Requires-Python: >=3.10
